LICENSE
pyproject.toml
setup.py
hqq/__init__.py
hqq.egg-info/PKG-INFO
hqq.egg-info/SOURCES.txt
hqq.egg-info/dependency_links.txt
hqq.egg-info/requires.txt
hqq.egg-info/top_level.txt
hqq/backends/__init__.py
hqq/backends/bitblas.py
hqq/backends/gemlite.py
hqq/backends/marlin.py
hqq/backends/torchao.py
hqq/core/__init__.py
hqq/core/bitpack.py
hqq/core/optimize.py
hqq/core/peft.py
hqq/core/quantize.py
hqq/core/utils.py
hqq/engine/__init__.py
hqq/engine/base.py
hqq/engine/hf.py
hqq/engine/timm.py
hqq/kernels/__init__.py
hqq/kernels/hqq_aten_cuda.cpp
hqq/kernels/hqq_aten_cuda_kernel.cu
hqq/kernels/hqq_aten_torch.cpp
hqq/kernels/setup_cuda.py
hqq/kernels/setup_torch.py
hqq/models/__init__.py
hqq/models/base.py
hqq/models/hf/__init__.py
hqq/models/hf/base.py
hqq/models/hf/llama.py
hqq/models/hf/mistral.py
hqq/models/hf/mixtral.py
hqq/models/hf/phi.py
hqq/models/hf/phi_opt.py
hqq/utils/__init__.py
hqq/utils/aria.py
hqq/utils/generation_hf.py
hqq/utils/patching.py
hqq/utils/vllm.py
tests/test_bitpack.py
tests/test_quantize.py