Metadata-Version: 2.1
Name: hqq
Version: 0.2.8.post1
Summary: Half-Quadratic Quantization (HQQ)
Home-page: https://github.com/mobiusml/hqq/
Author: Dr. Hicham Badri
Author-email: hicham@mobiuslabs.com
License: Apache 2
License-File: LICENSE
Requires-Dist: numpy>=1.24.4
Requires-Dist: tqdm>=4.64.1
Requires-Dist: einops
Requires-Dist: accelerate
Requires-Dist: transformers>=4.36.1
Requires-Dist: huggingface_hub
Requires-Dist: termcolor
